langtimezone/__init__.py
langtimezone/langtimezone.py
langtimezone/supplementalData.xml
langtimezone-0.1.2.dist-info/LICENSE
langtimezone-0.1.2.dist-info/METADATA
langtimezone-0.1.2.dist-info/WHEEL
langtimezone-0.1.2.dist-info/top_level.txt
langtimezone-0.1.2.dist-info/RECORD
