Metadata-Version: 2.1
Name: langtimezone
Version: 0.1.2
Summary: A Python library for extracting language and timezone based on country code.
Home-page: https://github.com/yourusername/langtimezone
Author: Amir Bargahi
Author-email: lightdevs666@gmail.com
Classifier: Programming Language :: Python :: 3
Classifier: License :: OSI Approved :: MIT License
Classifier: Operating System :: OS Independent
Requires-Python: >=3.6
License-File: LICENSE
Requires-Dist: pytz
Requires-Dist: lxml
Requires-Dist: phonenumbers
